<?xml version="1.0" encoding="utf-8"?>
<odoo>
  <data>

    <!-- Меню Продажи -->
    <menuitem id="menu_dino_sales" sequence="40"
        name="Sales" web_icon="dino_erp,core/menu_icons/sales.png"/>
        <menuitem id="menu_dino_sales_list" name="Sales list" parent="menu_dino_sales"
            action="action_dino_project_sales" sequence="1"/>


    <!-- Меню Банк -->
    <menuitem id="menu_dino_bank_root" sequence="50"
        name="Bank" web_icon="dino_erp,core/menu_icons/bank.png" action="action_dino_bank_transaction"/>
        <menuitem id="menu_dino_bank_transactions" name="Transactions" parent="menu_dino_bank_root"
            action="action_dino_bank_transaction" sequence="1"/>
        <menuitem id="menu_dino_bank_balance_history" name="Balances" parent="menu_dino_bank_root"
            action="action_dino_bank_balance_history" sequence="2"/>
        <menuitem id="menu_dino_bank_currency_rates" name="Currency Rates" parent="menu_dino_bank_root"
            action="action_dino_currency_rate" sequence="3"/>
        <menuitem id="menu_dino_bank_config" name="Configurations" parent="menu_dino_bank_root" sequence="100"/>
            <menuitem id="menu_dino_bank_integration_settings" name="Bank Directory" parent="menu_dino_bank_config"
                action="action_dino_bank_config" sequence="1"/>
            <menuitem id="menu_dino_currency_list" name="System Currencies" parent="menu_dino_bank_config"
                action="base.action_currency_form" sequence="2"/>
            <menuitem id="menu_res_currency_rates" name="System Rates" parent="menu_dino_bank_config"
                action="action_res_currency_rate" sequence="4"/>
            <menuitem id="menu_dino_company_list" name="Our Companies" parent="menu_dino_bank_config"
                action="base.action_res_company_form" sequence="5"/>

    <!-- Меню Касса -->
    <menuitem id="menu_dino_cashbook_root" sequence="51"
        name="Cashbook" web_icon="dino_erp,core/menu_icons/cash.png"/>
        <menuitem id="menu_dino_cashbook_transactions" name="Transactions" parent="menu_dino_cashbook_root"
            action="action_dino_cashbook" sequence="1"/>

    <!-- Меню Проекты -->
    <menuitem id="menu_dino_project_root" sequence="52"
        name="Projects" web_icon="dino_erp,core/menu_icons/project.png"/>
        <menuitem id="menu_dino_project_list" name="Projects List" parent="menu_dino_project_root"
            action="action_dino_project" sequence="1"/>
        <menuitem id="menu_dino_project_purchases" name="Purchase Projects" parent="menu_dino_project_root"
            action="action_dino_project_purchases" sequence="3"/>

    <!-- Меню Документы -->
    <menuitem id="menu_dino_documents_root" sequence="53"
        name="Documents" web_icon="dino_erp,core/menu_icons/docs.png"/>

        <menuitem id="menu_dino_document_list" name="Document List" parent="menu_dino_documents_root" sequence="1"
            action="action_dino_operation_document_list"/>

        <menuitem id="menu_dino_document_md" name="Master Data" parent="menu_dino_documents_root" sequence="2"/>
             <menuitem id="menu_dino_document_partner_list" parent="menu_dino_document_md" name="Partner List" sequence="1"
                action="action_dino_partner_list"/>
             <menuitem id="menu_dino_partner_nomenclature_list" parent="menu_dino_document_md" name="Partner Nomenclature" sequence="2"
                action="action_dino_partner_nomenclature_list"/>

        <menuitem id="menu_dino_documents_config" name="Configurations" parent="menu_dino_documents_root" sequence="100"/>
            <menuitem id="menu_dino_document_type" name="Document Types" parent="menu_dino_documents_config"
                action="action_dino_document_type" sequence="1"/>
            <menuitem id="menu_dino_parser_agent" name="Parser Agents" parent="menu_dino_documents_config"
                action="action_dino_parser_agent" sequence="2"/>


    <!-- Меню Контрагенты -->
    <menuitem id="menu_dino_partners_root" sequence="54"
        name="Partners" web_icon="dino_erp,core/menu_icons/partners.png"/>
        <menuitem id="menu_dino_partner_nomenclature_main" parent="menu_dino_partners_root" name="Partner Nomenclature" sequence="1"
            action="action_dino_partner_nomenclature_list"/>
        <menuitem id="menu_dino_partner_main" parent="menu_dino_partners_root" name="Partner List" sequence="2"
            action="action_dino_partner_list"/>
        <menuitem id="menu_dino_partners_config" parent="menu_dino_partners_root" name="Configurations" sequence="10"/>
            <menuitem id="menu_dino_partner_tag_config" parent="menu_dino_partners_config" name="Partner Types" sequence="10"
                action="action_dino_partner_tag_list"/>
            <menuitem id="menu_dino_tax_system_config" parent="menu_dino_partners_config" name="Tax Systems" sequence="20"
                action="action_dino_tax_system_list"/>

    <!-- Меню Закупки -->
    <menuitem id="menu_dino_purchases" name="Purchases" sequence="60"
        web_icon="dino_erp,core/menu_icons/purchases.png"/>
        <menuitem id="menu_dino_purchases_list" name="Purchase Projects" parent="menu_dino_purchases"
            action="action_dino_project_purchases" sequence="3"/>


    <!-- Меню Склад -->
    <menuitem id="menu_dino_stock_root" name="Stock" sequence="70"
        web_icon="dino_erp,core/menu_icons/stock.png"/>
        <menuitem id="menu_dino_stock_families" name="Components" parent="menu_dino_stock_root"
            action="dino_component_action" sequence="1"/>
        <menuitem id="menu_dino_stock_nomenclatures" name="Nomenclature" parent="menu_dino_stock_root"
            action="dino_nomenclature_action" sequence="2"/>
        <menuitem id="menu_dino_stock_config" name="Configurations" parent="menu_dino_stock_root" sequence="10"/>
            <menuitem id="menu_dino_stock_categories" name="Categories" parent="menu_dino_stock_config"
                action="dino_component_category_action" sequence="1"/>
            <menuitem id="menu_dino_stock_uom" name="Units of Measure" parent="menu_dino_stock_config"
                action="dino_uom_action" sequence="2"/>

   <!-- API Integration в Bank меню -->
   <menuitem id="menu_dino_api_integration"
             name="API Integration"
             parent="menu_dino_bank_root"
             action="action_dino_api_endpoint_list"
             sequence="10"/>


  </data>
</odoo>